MANIFEST.in
account_chart_en.xml
account_chart_fr.xml
account_chart_template_en.xml
account_chart_template_fr.xml
account_tax_code_en.xml
account_tax_code_fr.xml
account_tax_en.xml
account_tax_fr.xml
fiscal_templates_en.xml
fiscal_templates_fr.xml
l10n_ca_wizard.xml
setup.py
./__init__.py
./__openerp__.py
doc/Taxes.csv
i18n/ar.po
i18n/ca.po
i18n/da.po
i18n/de.po
i18n/en_GB.po
i18n/es.po
i18n/es_CR.po
i18n/es_MX.po
i18n/es_PY.po
i18n/es_VE.po
i18n/fr.po
i18n/gl.po
i18n/hu.po
i18n/it.po
i18n/l10n_ca_en.pot
i18n/nb.po
i18n/nl.po
i18n/pt.po
i18n/pt_BR.po
i18n/sl.po
i18n/sr@latin.po
i18n/tr.po
i18n/zh_CN.po
images/config_chart_l10n_ca.jpeg
images/l10n_ca_chart.jpeg
openerp_l10n_ca.egg-info/PKG-INFO
openerp_l10n_ca.egg-info/SOURCES.txt
openerp_l10n_ca.egg-info/dependency_links.txt
openerp_l10n_ca.egg-info/requires.txt
openerp_l10n_ca.egg-info/top_level.txt
static/src/img/icon.png